code_typer/__init__.py
code_typer/__main__.py
code_typer/_fast_human.cpython-313-x86_64-linux-gnu.so
code_typer/_fast_human.pyx
code_typer/_human_behavior_fast.pyx
code_typer/cli.py
code_typer/code_analyzer.py
code_typer/file_handler.py
code_typer/human_behavior.py
code_typer/py.typed
code_typer/python_simulator.py
code_typer/realistic_python_typer.py
code_typer/smart_python_typer.py
code_typer/typer_engine.py
code_typer/display/__init__.py
code_typer/display/ncurses_display.py
code_typer/syntax/__init__.py
code_typer/syntax/highlighter.py
code_typer/syntax/python.py
code_typer/syntax/sql.py
code_typer-0.1.1.dist-info/METADATA
code_typer-0.1.1.dist-info/WHEEL
code_typer-0.1.1.dist-info/entry_points.txt
code_typer-0.1.1.dist-info/top_level.txt
code_typer-0.1.1.dist-info/RECORD
code_typer-0.1.1.dist-info/licenses/LICENSE
