Metadata-Version: 2.4
Name: code-typer
Version: 0.1.1
Summary: Terminal-based code showcase tool that simulates human-like typing
Author-email: Farshid Ashouri <farsheed.ashouri@gmail.com>
Maintainer-email: Farshid Ashouri <farsheed.ashouri@gmail.com>
License-Expression: Apache-2.0
Project-URL: Homepage, https://github.com/rodmena-limited/code-typer
Project-URL: Repository, https://github.com/rodmena-limited/code-typer
Project-URL: Issues, https://github.com/rodmena-limited/code-typer/issues
Project-URL: Changelog, https://github.com/rodmena-limited/code-typer/releases
Keywords: terminal,code,demo,typing,showcase,conference,presentation,curses,ncurses,syntax-highlighting
Classifier: Development Status :: 4 - Beta
Classifier: Environment :: Console
Classifier: Environment :: Console :: Curses
Classifier: Intended Audience :: Developers
Classifier: Intended Audience :: Education
Classifier: Operating System :: POSIX
Classifier: Operating System :: POSIX :: Linux
Classifier: Operating System :: MacOS
Classifier: Operating System :: MacOS :: MacOS X
Classifier: Programming Language :: Python :: 3
Classifier: Programming Language :: Python :: 3.9
Classifier: Programming Language :: Python :: 3.10
Classifier: Programming Language :: Python :: 3.11
Classifier: Programming Language :: Python :: 3.12
Classifier: Programming Language :: Python :: 3.13
Classifier: Programming Language :: Cython
Classifier: Programming Language :: Python :: Implementation :: CPython
Classifier: Topic :: Software Development :: Libraries :: Python Modules
Classifier: Topic :: Terminals
Classifier: Topic :: Multimedia :: Graphics :: Presentation
Classifier: Typing :: Typed
Requires-Python: >=3.9
License-File: LICENSE
Requires-Dist: click>=8.0
Provides-Extra: dev
Requires-Dist: pytest>=7.0; extra == "dev"
Requires-Dist: pytest-cov>=4.0; extra == "dev"
Requires-Dist: ruff>=0.1.0; extra == "dev"
Requires-Dist: mypy>=1.0; extra == "dev"
Requires-Dist: Cython>=3.0; extra == "dev"
Requires-Dist: build; extra == "dev"
Requires-Dist: twine; extra == "dev"
Dynamic: license-file
